rappmysql/__init__.py
rappmysql/control.py
rappmysql/online.py
rappmysql/pass_check.py
rappmysql/sql/2024_04_19_auto.sql
rappmysql/static/heroku.ini
rappmysql/static/kalendar.ini
rappmysql/static/users.ini
rappmysql/templates/base.html
rappmysql/templates/blabla.html
rappmysql/templates/cheltuieli.html
rappmysql/templates/expenses.html
rappmysql/templates/index.html
rappmysql/templates/kalendar.html
rappmysql/templates/login.html
rappmysql/templates/masina.html
rappmysql/templates/navbar.html
rappmysql/templates/register.html
rappmysql/templates/side_navbar.html
rappmysql-0.1.0.dist-info/METADATA
rappmysql-0.1.0.dist-info/WHEEL
rappmysql-0.1.0.dist-info/top_level.txt
rappmysql-0.1.0.dist-info/RECORD
