Metadata-Version: 2.1
Name: rappmysql
Version: 0.1.0
Summary: aplicatia mea personala
Home-page: https://github.com/RaduMirc/rappmysql.git
Author: Radu M.
Author-email: radu.mircea@yahoo.com
Project-URL: Bug Tracker, https://github.com/RaduMirc/rappmysql.git
Classifier: Programming Language :: Python :: 3
Classifier: License :: OSI Approved :: MIT License
Classifier: Operating System :: OS Independent
Requires-Python: >=3.6
